setup.py
client/__init__.py
client/client.py
client/base/__init__.py
client/base/descriptors.py
client/base/metaclasses.py
client/base/utils.py
client/base/variables.py
client/client/__init__.py
client/client/add_contact.py
client/client/client_ui_conv.py
client/client/database.py
client/client/del_contact.py
client/client/main_window.py
client/client/start_dialog.py
client/client/transport.py
client/log/__init__.py
client/log/config/__init__.py
client/log/config/client_log_config.py
mess_client_december.egg-info/PKG-INFO
mess_client_december.egg-info/SOURCES.txt
mess_client_december.egg-info/dependency_links.txt
mess_client_december.egg-info/requires.txt
mess_client_december.egg-info/top_level.txt