Metadata-Version: 1.0
Name: mess-client-december
Version: 0.0.1
Summary: mess_client_december
Home-page: UNKNOWN
Author: Alex Morev
Author-email: iv.iv@yandex.ru
License: UNKNOWN
Platform: UNKNOWN
